{
  "source": "Allen Institute mouse brain (root compartment, structure 997)",
  "axes": {
    "X": "ML",
    "Y": "DV",
    "Z": "AP"
  },
  "allenBboxUm": {
    "min": [
      487.539429,
      137.430908,
      3.140656
    ],
    "max": [
      10887.547852,
      7561.789062,
      13187.62207
    ],
    "size": [
      10400.008423,
      7424.358154,
      13184.481414
    ]
  },
  "centerUm": [
    5687.5436405,
    3849.609985,
    6595.3813629999995
  ],
  "scale": 0.00015169349003566352,
  "yFlipped": true,
  "exportedFaces": 59999,
  "nInteriorDots": 16000,
  "landmarks": {
    "visp_right": [
      0.30527652871702093,
      0.32608184084016034,
      0.2889182482334986
    ],
    "visp_left": [
      -0.3014974314256332,
      0.32608184084016034,
      0.2889182482334986
    ]
  }
}